{
  "operationid": 781,
  "productid": 735,
  "code": "ZCUS",
  "pname": "Electrochromatic rearview mirror",
  "parentid": null,
  "start_date": "2023-01-01 00:00:00.000000",
  "delivery_date": "2023-03-01 00:00:00.000000",
  "quantity": 7,
  "machines": [
    {
      "id": 1,
      "name": "Machine_01",
      "oee": 0.95,
      "execution_time": 94,
      "setup_time": 5400
    },
    {
      "id": 3,
      "name": "Machine_03",
      "oee": 0.895,
      "execution_time": 100,
      "setup_time": 7200
    },
    {
      "id": 4,
      "name": "Machine_04",
      "oee": 0.942,
      "execution_time": 95,
      "setup_time": 7200
    },
    {
      "id": 8,
      "name": "Machine_08",
      "oee": 0.833,
      "execution_time": 108,
      "setup_time": 7200
    }
  ],
  "metainfo": {
    "operations_list": [
      781,
      782,
      783,
      784,
      785,
      786,
      787,
      788,
      789,
      790,
      791,
      792,
      793,
      794,
      795,
      796,
      797,
      798,
      799,
      800,
      801
    ],
    "machines_list": [
      1,
      2,
      3,
      4,
      5,
      6,
      7,
      8,
      9,
      10
    ],
    "maintenances": [
      {
        "id": 802,
        "machineid": 1,
        "start_date": "2023-01-10 00:00:00.000000",
        "end_date": "2023-01-10 06:00:00.000000"
      },
      {
        "id": 808,
        "machineid": 1,
        "start_date": "2023-02-04 03:00:00.000000",
        "end_date": "2023-02-04 06:00:00.000000"
      },
      {
        "id": 809,
        "machineid": 2,
        "start_date": "2023-02-04 04:00:00.000000",
        "end_date": "2023-02-04 08:00:00.000000"
      },
      {
        "id": 814,
        "machineid": 2,
        "start_date": "2023-02-10 09:00:00.000000",
        "end_date": "2023-02-10 12:00:00.000000"
      },
      {
        "id": 815,
        "machineid": 2,
        "start_date": "2023-02-12 15:00:00.000000",
        "end_date": "2023-02-12 18:00:00.000000"
      },
      {
        "id": 804,
        "machineid": 3,
        "start_date": "2023-01-28 13:00:00.000000",
        "end_date": "2023-01-28 17:00:00.000000"
      },
      {
        "id": 810,
        "machineid": 3,
        "start_date": "2023-01-30 06:00:00.000000",
        "end_date": "2023-01-30 12:00:00.000000"
      },
      {
        "id": 803,
        "machineid": 4,
        "start_date": "2023-01-09 10:00:00.000000",
        "end_date": "2023-01-09 13:00:00.000000"
      },
      {
        "id": 811,
        "machineid": 4,
        "start_date": "2023-01-31 00:00:00.000000",
        "end_date": "2023-01-31 03:00:00.000000"
      },
      {
        "id": 817,
        "machineid": 5,
        "start_date": "2023-02-19 04:00:00.000000",
        "end_date": "2023-02-19 10:00:00.000000"
      },
      {
        "id": 805,
        "machineid": 6,
        "start_date": "2023-01-22 05:00:00.000000",
        "end_date": "2023-01-22 11:00:00.000000"
      },
      {
        "id": 818,
        "machineid": 6,
        "start_date": "2023-02-19 12:00:00.000000",
        "end_date": "2023-02-19 18:00:00.000000"
      },
      {
        "id": 806,
        "machineid": 7,
        "start_date": "2023-01-24 09:00:00.000000",
        "end_date": "2023-01-24 12:00:00.000000"
      },
      {
        "id": 812,
        "machineid": 7,
        "start_date": "2023-01-29 06:00:00.000000",
        "end_date": "2023-01-29 12:00:00.000000"
      },
      {
        "id": 819,
        "machineid": 7,
        "start_date": "2023-02-24 04:00:00.000000",
        "end_date": "2023-02-24 10:00:00.000000"
      },
      {
        "id": 816,
        "machineid": 8,
        "start_date": "2023-02-17 01:00:00.000000",
        "end_date": "2023-02-17 07:00:00.000000"
      },
      {
        "id": 807,
        "machineid": 10,
        "start_date": "2023-01-23 14:00:00.000000",
        "end_date": "2023-01-23 17:00:00.000000"
      },
      {
        "id": 813,
        "machineid": 10,
        "start_date": "2023-01-29 19:00:00.000000",
        "end_date": "2023-01-30 01:00:00.000000"
      }
    ]
  },
  "name": "root",
  "children": [
    {
      "parentid": 781,
      "operationid": 782,
      "productid": 775,
      "code": "HYDY",
      "pname": "Bolstering",
      "quantity": 7,
      "machines": [
        {
          "id": 2,
          "name": "Machine_02",
          "oee": 0.895,
          "execution_time": 134,
          "setup_time": 5400
        },
        {
          "id": 6,
          "name": "Machine_06",
          "oee": 0.958,
          "execution_time": 125,
          "setup_time": 7200
        },
        {
          "id": 8,
          "name": "Machine_08",
          "oee": 0.833,
          "execution_time": 144,
          "setup_time": 3600
        },
        {
          "id": 9,
          "name": "Machine_09",
          "oee": 0.866,
          "execution_time": 138,
          "setup_time": 7200
        }
      ],
      "name": "s0",
      "children": [
        {
          "parentid": 782,
          "operationid": 783,
          "productid": 591,
          "code": "LKPJ",
          "pname": "Crankcase ventilation filter",
          "quantity": 5,
          "machines": [
            {
              "id": 1,
              "name": "Machine_01",
              "oee": 0.95,
              "execution_time": 63,
              "setup_time": 7200
            },
            {
              "id": 4,
              "name": "Machine_04",
              "oee": 0.942,
              "execution_time": 63,
              "setup_time": 7200
            }
          ],
          "name": "s0",
          "raw_material_id": 573,
          "raw_material_quantity": 8
        },
        {
          "parentid": 782,
          "operationid": 784,
          "productid": 684,
          "code": "AKME",
          "pname": "Self-leveling headlights",
          "quantity": 5,
          "machines": [
            {
              "id": 6,
              "name": "Machine_06",
              "oee": 0.958,
              "execution_time": 125,
              "setup_time": 3600
            }
          ],
          "name": "s1",
          "raw_material_id": 571,
          "raw_material_quantity": 6
        },
        {
          "parentid": 782,
          "operationid": 785,
          "productid": 730,
          "code": "XTFM",
          "pname": "Automatic transmission",
          "quantity": 4,
          "machines": [
            {
              "id": 2,
              "name": "Machine_02",
              "oee": 0.895,
              "execution_time": 100,
              "setup_time": 5400
            },
            {
              "id": 3,
              "name": "Machine_03",
              "oee": 0.895,
              "execution_time": 100,
              "setup_time": 7200
            },
            {
              "id": 4,
              "name": "Machine_04",
              "oee": 0.942,
              "execution_time": 95,
              "setup_time": 7200
            },
            {
              "id": 6,
              "name": "Machine_06",
              "oee": 0.958,
              "execution_time": 93,
              "setup_time": 3600
            },
            {
              "id": 10,
              "name": "Machine_10",
              "oee": 0.942,
              "execution_time": 95,
              "setup_time": 7200
            }
          ],
          "name": "s2",
          "raw_material_id": 573,
          "raw_material_quantity": 3
        },
        {
          "parentid": 782,
          "operationid": 786,
          "productid": 653,
          "code": "MANI",
          "pname": "Heater",
          "quantity": 3,
          "machines": [
            {
              "id": 6,
              "name": "Machine_06",
              "oee": 0.958,
              "execution_time": 62,
              "setup_time": 3600
            },
            {
              "id": 7,
              "name": "Machine_07",
              "oee": 0.91,
              "execution_time": 65,
              "setup_time": 5400
            }
          ],
          "name": "s3",
          "raw_material_id": 547,
          "raw_material_quantity": 10
        }
      ]
    },
    {
      "parentid": 781,
      "operationid": 787,
      "productid": 645,
      "code": "OJAH",
      "pname": "Knee airbags",
      "quantity": 9,
      "machines": [
        {
          "id": 1,
          "name": "Machine_01",
          "oee": 0.95,
          "execution_time": 126,
          "setup_time": 3600
        },
        {
          "id": 2,
          "name": "Machine_02",
          "oee": 0.895,
          "execution_time": 134,
          "setup_time": 3600
        },
        {
          "id": 4,
          "name": "Machine_04",
          "oee": 0.942,
          "execution_time": 127,
          "setup_time": 3600
        },
        {
          "id": 6,
          "name": "Machine_06",
          "oee": 0.958,
          "execution_time": 125,
          "setup_time": 7200
        }
      ],
      "name": "s1",
      "children": [
        {
          "parentid": 787,
          "operationid": 788,
          "productid": 761,
          "code": "KGNQ",
          "pname": "Headlight washers",
          "quantity": 10,
          "machines": [
            {
              "id": 3,
              "name": "Machine_03",
              "oee": 0.895,
              "execution_time": 100,
              "setup_time": 7200
            },
            {
              "id": 4,
              "name": "Machine_04",
              "oee": 0.942,
              "execution_time": 95,
              "setup_time": 3600
            },
            {
              "id": 5,
              "name": "Machine_05",
              "oee": 0.81,
              "execution_time": 111,
              "setup_time": 7200
            },
            {
              "id": 6,
              "name": "Machine_06",
              "oee": 0.958,
              "execution_time": 93,
              "setup_time": 5400
            },
            {
              "id": 7,
              "name": "Machine_07",
              "oee": 0.91,
              "execution_time": 98,
              "setup_time": 5400
            }
          ],
          "name": "s0",
          "raw_material_id": 550,
          "raw_material_quantity": 5
        },
        {
          "parentid": 787,
          "operationid": 789,
          "productid": 606,
          "code": "ILJY",
          "pname": "Radio data system",
          "quantity": 2,
          "machines": [
            {
              "id": 1,
              "name": "Machine_01",
              "oee": 0.95,
              "execution_time": 126,
              "setup_time": 5400
            },
            {
              "id": 6,
              "name": "Machine_06",
              "oee": 0.958,
              "execution_time": 125,
              "setup_time": 3600
            },
            {
              "id": 7,
              "name": "Machine_07",
              "oee": 0.91,
              "execution_time": 131,
              "setup_time": 5400
            },
            {
              "id": 8,
              "name": "Machine_08",
              "oee": 0.833,
              "execution_time": 144,
              "setup_time": 7200
            },
            {
              "id": 10,
              "name": "Machine_10",
              "oee": 0.942,
              "execution_time": 127,
              "setup_time": 7200
            }
          ],
          "name": "s1",
          "raw_material_id": 562,
          "raw_material_quantity": 8
        },
        {
          "parentid": 787,
          "operationid": 790,
          "productid": 724,
          "code": "RXRE",
          "pname": "Brake linings",
          "quantity": 2,
          "machines": [
            {
              "id": 7,
              "name": "Machine_07",
              "oee": 0.91,
              "execution_time": 131,
              "setup_time": 7200
            }
          ],
          "name": "s2",
          "raw_material_id": 563,
          "raw_material_quantity": 7
        },
        {
          "parentid": 787,
          "operationid": 791,
          "productid": 661,
          "code": "SRIV",
          "pname": "Air conditioning filter",
          "quantity": 10,
          "machines": [
            {
              "id": 9,
              "name": "Machine_09",
              "oee": 0.866,
              "execution_time": 138,
              "setup_time": 7200
            }
          ],
          "name": "s3",
          "raw_material_id": 554,
          "raw_material_quantity": 9
        }
      ]
    },
    {
      "parentid": 781,
      "operationid": 792,
      "productid": 703,
      "code": "QUZJ",
      "pname": "Air conditioning filter",
      "quantity": 8,
      "machines": [
        {
          "id": 3,
          "name": "Machine_03",
          "oee": 0.895,
          "execution_time": 100,
          "setup_time": 3600
        }
      ],
      "name": "s2",
      "children": [
        {
          "parentid": 792,
          "operationid": 793,
          "productid": 714,
          "code": "HPMH",
          "pname": "Dynamic brake control",
          "quantity": 5,
          "machines": [
            {
              "id": 2,
              "name": "Machine_02",
              "oee": 0.895,
              "execution_time": 134,
              "setup_time": 3600
            },
            {
              "id": 7,
              "name": "Machine_07",
              "oee": 0.91,
              "execution_time": 131,
              "setup_time": 7200
            },
            {
              "id": 9,
              "name": "Machine_09",
              "oee": 0.866,
              "execution_time": 138,
              "setup_time": 3600
            }
          ],
          "name": "s0",
          "raw_material_id": 544,
          "raw_material_quantity": 9
        },
        {
          "parentid": 792,
          "operationid": 794,
          "productid": 584,
          "code": "YEXA",
          "pname": "Fog lights",
          "quantity": 2,
          "machines": [
            {
              "id": 7,
              "name": "Machine_07",
              "oee": 0.91,
              "execution_time": 65,
              "setup_time": 3600
            }
          ],
          "name": "s1",
          "raw_material_id": 566,
          "raw_material_quantity": 1
        },
        {
          "parentid": 792,
          "operationid": 795,
          "productid": 737,
          "code": "FHRL",
          "pname": "Brake booster",
          "quantity": 8,
          "machines": [
            {
              "id": 3,
              "name": "Machine_03",
              "oee": 0.895,
              "execution_time": 134,
              "setup_time": 3600
            },
            {
              "id": 4,
              "name": "Machine_04",
              "oee": 0.942,
              "execution_time": 127,
              "setup_time": 7200
            },
            {
              "id": 7,
              "name": "Machine_07",
              "oee": 0.91,
              "execution_time": 131,
              "setup_time": 3600
            },
            {
              "id": 8,
              "name": "Machine_08",
              "oee": 0.833,
              "execution_time": 144,
              "setup_time": 7200
            },
            {
              "id": 9,
              "name": "Machine_09",
              "oee": 0.866,
              "execution_time": 138,
              "setup_time": 5400
            }
          ],
          "name": "s2",
          "raw_material_id": 562,
          "raw_material_quantity": 4
        },
        {
          "parentid": 792,
          "operationid": 796,
          "productid": 767,
          "code": "QVCG",
          "pname": "Cruise control",
          "quantity": 6,
          "machines": [
            {
              "id": 3,
              "name": "Machine_03",
              "oee": 0.895,
              "execution_time": 134,
              "setup_time": 3600
            },
            {
              "id": 6,
              "name": "Machine_06",
              "oee": 0.958,
              "execution_time": 125,
              "setup_time": 3600
            },
            {
              "id": 8,
              "name": "Machine_08",
              "oee": 0.833,
              "execution_time": 144,
              "setup_time": 5400
            }
          ],
          "name": "s3",
          "raw_material_id": 545,
          "raw_material_quantity": 4
        }
      ]
    },
    {
      "parentid": 781,
      "operationid": 797,
      "productid": 726,
      "code": "VDZN",
      "pname": "Separate rear audio",
      "quantity": 4,
      "machines": [
        {
          "id": 5,
          "name": "Machine_05",
          "oee": 0.81,
          "execution_time": 74,
          "setup_time": 3600
        },
        {
          "id": 6,
          "name": "Machine_06",
          "oee": 0.958,
          "execution_time": 62,
          "setup_time": 3600
        },
        {
          "id": 10,
          "name": "Machine_10",
          "oee": 0.942,
          "execution_time": 63,
          "setup_time": 3600
        }
      ],
      "name": "s3",
      "children": [
        {
          "parentid": 797,
          "operationid": 798,
          "productid": 642,
          "code": "MEFQ",
          "pname": "Automatic door unlock",
          "quantity": 3,
          "machines": [
            {
              "id": 3,
              "name": "Machine_03",
              "oee": 0.895,
              "execution_time": 67,
              "setup_time": 7200
            }
          ],
          "name": "s0",
          "raw_material_id": 575,
          "raw_material_quantity": 8
        },
        {
          "parentid": 797,
          "operationid": 799,
          "productid": 604,
          "code": "CVPY",
          "pname": "Climate control",
          "quantity": 2,
          "machines": [
            {
              "id": 7,
              "name": "Machine_07",
              "oee": 0.91,
              "execution_time": 131,
              "setup_time": 5400
            },
            {
              "id": 8,
              "name": "Machine_08",
              "oee": 0.833,
              "execution_time": 144,
              "setup_time": 3600
            }
          ],
          "name": "s1",
          "raw_material_id": 561,
          "raw_material_quantity": 9
        },
        {
          "parentid": 797,
          "operationid": 800,
          "productid": 706,
          "code": "UVMB",
          "pname": "Child seat anchors",
          "quantity": 2,
          "machines": [
            {
              "id": 8,
              "name": "Machine_08",
              "oee": 0.833,
              "execution_time": 108,
              "setup_time": 7200
            }
          ],
          "name": "s2",
          "raw_material_id": 560,
          "raw_material_quantity": 9
        },
        {
          "parentid": 797,
          "operationid": 801,
          "productid": 655,
          "code": "HAZF",
          "pname": "Satellite radio",
          "quantity": 2,
          "machines": [
            {
              "id": 2,
              "name": "Machine_02",
              "oee": 0.895,
              "execution_time": 67,
              "setup_time": 7200
            },
            {
              "id": 3,
              "name": "Machine_03",
              "oee": 0.895,
              "execution_time": 67,
              "setup_time": 5400
            },
            {
              "id": 6,
              "name": "Machine_06",
              "oee": 0.958,
              "execution_time": 62,
              "setup_time": 3600
            },
            {
              "id": 7,
              "name": "Machine_07",
              "oee": 0.91,
              "execution_time": 65,
              "setup_time": 7200
            },
            {
              "id": 9,
              "name": "Machine_09",
              "oee": 0.866,
              "execution_time": 69,
              "setup_time": 3600
            }
          ],
          "name": "s3",
          "raw_material_id": 576,
          "raw_material_quantity": 6
        }
      ]
    }
  ]
}